ccd_deidentification/__init__.py
ccd_deidentification/deidentifier.py
ccd_deidentification/main.py
tests/__init__.py
tests/test_deidentifier.py
ccd_deidentification-0.2.1.dist-info/METADATA
ccd_deidentification-0.2.1.dist-info/WHEEL
ccd_deidentification-0.2.1.dist-info/entry_points.txt
ccd_deidentification-0.2.1.dist-info/top_level.txt
ccd_deidentification-0.2.1.dist-info/RECORD
