Metadata-Version: 2.4
Name: ccd_deidentification
Version: 0.2.1
Requires-Dist: lxml~=5.3.0
Requires-Dist: spacy~=3.8.5
Requires-Dist: pydantic
Requires-Dist: jinja2
Requires-Dist: markupsafe
Requires-Dist: setuptools~=75.1.0
Requires-Dist: pandas
Dynamic: description
Dynamic: description-content-type
Dynamic: requires-dist
